fuzz_automata/__init__.py
fuzz_automata/fanmap.py
fuzz_automata/fuzzer.py
fuzz_automata/logger.py
fuzz_automata/main.py
fuzz_automata/mutator.py
fuzz_automata/player.py
fuzz_automata/portablescript.py
fuzz_automata/protocol.py
fuzz_automata/protocolextractor.py
fuzz_automata/protocolset.py
fuzz_automata/proxy.py
fuzz_automata/wsmask.py
fuzz_automata_kahiroka-0.0.7.dist-info/LICENSE
fuzz_automata_kahiroka-0.0.7.dist-info/METADATA
fuzz_automata_kahiroka-0.0.7.dist-info/WHEEL
fuzz_automata_kahiroka-0.0.7.dist-info/entry_points.txt
fuzz_automata_kahiroka-0.0.7.dist-info/top_level.txt
fuzz_automata_kahiroka-0.0.7.dist-info/RECORD
