Metadata-Version: 2.1
Name: fuzz-automata-kahiroka
Version: 0.0.7
Summary: Seed-based random network fuzzer
Home-page: https://github.com/kahiroka/fuzz-automata
Author: kahiroka
Author-email: 
License: MIT License
Project-URL: Bug Tracker, https://github.com/kahiroka/fuzz-automata/issues
Classifier: Topic :: Security
Classifier: Topic :: Software Development :: Testing
Requires-Python: >=3.6
License-File: LICENSE
Requires-Dist: pwntools (>=4.7.0)
Requires-Dist: pyradamsa (>=0.1.1)
Requires-Dist: python-nmap (>=0.7.1)
Requires-Dist: scapy (>=2.4.5)
Requires-Dist: msgpack (>=1.0.3)
